buteo/__init__.py
buteo/ai/__init__.py
buteo/ai/augmentation.py
buteo/ai/augmentation_funcs.py
buteo/ai/augmentation_utils.py
buteo/ai/encoding.py
buteo/ai/masking.py
buteo/ai/masking_funcs.py
buteo/ai/scalers.py
buteo/ai/selection.py
buteo/ai/spatial_label_smoothing.py
buteo/array/__init__.py
buteo/array/color.py
buteo/array/convolution.py
buteo/array/convolution_funcs.py
buteo/array/convolution_kernels.py
buteo/array/distance.py
buteo/array/edge_detection.py
buteo/array/fill.py
buteo/array/filters.py
buteo/array/loaders.py
buteo/array/morphology.py
buteo/array/patches.py
buteo/array/timeseries.py
buteo/array/utils_array.py
buteo/bindings/__init__.py
buteo/bindings/orfeo.py
buteo/eo/__init__.py
buteo/eo/s1_preprocess.py
buteo/eo/s1_utils.py
buteo/eo/s2_indices.py
buteo/eo/s2_utils.py
buteo/eo/xyz_tiles.py
buteo/eo/graphs/L2A_GIPP.xml
buteo/eo/graphs/step_01_backstatter.xml
buteo/eo/graphs/step_01_coherence.xml
buteo/eo/graphs/step_02_backscatter.xml
buteo/eo/graphs/step_02_backscatter_speckle.xml
buteo/eo/graphs/step_02_coherence.xml
buteo/raster/__init__.py
buteo/raster/align.py
buteo/raster/borders.py
buteo/raster/clip.py
buteo/raster/coordinates.py
buteo/raster/core_offsets.py
buteo/raster/core_raster.py
buteo/raster/core_raster_io.py
buteo/raster/core_stack.py
buteo/raster/coregister.py
buteo/raster/datatype.py
buteo/raster/dem.py
buteo/raster/footprints.py
buteo/raster/gefolki.py
buteo/raster/grid.py
buteo/raster/metadata.py
buteo/raster/nodata.py
buteo/raster/proximity.py
buteo/raster/reproject.py
buteo/raster/resample.py
buteo/raster/shift.py
buteo/raster/vectorize.py
buteo/raster/warp.py
buteo/raster/zonal_statistics.py
buteo/utils/__init__.py
buteo/utils/utils_aux.py
buteo/utils/utils_base.py
buteo/utils/utils_bbox.py
buteo/utils/utils_gdal.py
buteo/utils/utils_io.py
buteo/utils/utils_path.py
buteo/utils/utils_projection.py
buteo/utils/utils_translate.py
buteo/vector/__init__.py
buteo/vector/buffer.py
buteo/vector/clip.py
buteo/vector/convert_parts.py
buteo-0.9.64.dist-info/LICENSE
buteo-0.9.64.dist-info/WHEEL
buteo-0.9.64.dist-info/METADATA
buteo-0.9.64.dist-info/RECORD
