Metadata-Version: 2.3
Name: buteo
Version: 0.9.64
Summary: Tools for merging Geospatial Analysis and AI.
Author-email: Casper Fibaek <casperfibaek@gmail.com>
Requires-Python: >=3.7
Classifier: Programming Language :: Python :: 3
Classifier: License :: OSI Approved :: MIT License
Classifier: Operating System :: OS Independent
Requires-Dist: numba>=0.56.4
Requires-Dist: psutil>=5.9.5
Requires-Dist: tqdm>=4.65.0
Project-URL: Bug Tracker, https://github.com/casperfibaek/buteo/issues
Project-URL: Homepage, https://github.com/casperfibaek/buteo
